Workbook

Sheet Historical_Data
A1: Historical Data (enter 12+ months)
A3: Month (e.g., 2024-01) | B3: Revenue (£) | C3: Expenses (£) | D3: Net Profit (£) | E3: Cash Balance (£)
A4: 2024-01 | B4: 25690 | C4: 17500 | D4: =B4-C4 -> 8190 | E4: 8190
A5: 2024-02 | B5: 28000 | C5: 19560 | D5: =B5-C5 -> 8440 | E5: =E4+D5 -> 16630
A6: 2024-03 | B6: 32000 | C6: 21560 | D6: =B6-C6 -> 10440 | E6: =E5+D6 -> 27070
A7: 2024-04 | B7: 35000 | C7: 22000 | D7: =B7-C7 -> 13000 | E7: =E6+D7 -> 40070
A8: 2024-05 | B8: 36989 | C8: 23000 | D8: =B8-C8 -> 13989 | E8: =E7+D8 -> 54059
A9: 2024-06 | B9: 39000 | C9: 25060 | D9: =B9-C9 -> 13940 | E9: =E8+D9 -> 67999
A10: 2024-07 | B10: 40254 | C10: 28000 | D10: =B10-C10 -> 12254 | E10: =E9+D10 -> 80253
A11: 2024-08 | B11: 42100 | C11: 29000 | D11: =B11-C11 -> 13100 | E11: =E10+D11 -> 93353
A12: 2024-09 | B12: 45000 | C12: 30500 | D12: =B12-C12 -> 14500 | E12: =E11+D12 -> 107853
A13: 2024-10 | B13: 47856 | C13: 32000 | D13: =B13-C13 -> 15856 | E13: =E12+D13 -> 123709
A14: 2024-11 | B14: 49000 | C14: 33500 | D14: =B14-C14 -> 15500 | E14: =E13+D14 -> 139209
A15: 2024-12 | B15: 50000 | C15: 34506 | D15: =B15-C15 -> 15494 | E15: =E14+D15 -> 154703

Sheet Assumptions
A1: Assumptions (edit values)
A3: Assumption | B3: Base Case | C3: Best Case | D3: Worst Case | E3: Notes
A4: Revenue Growth % (MoM) | B4: 0.05 | C4: 0.08 | D4: 0.02 | E4: Monthly growth rate applied to last month revenue
A5: Expense Growth % (MoM) | B5: 0.03 | C5: 0.02 | D5: 0.06 | E5: Monthly growth rate applied to last month expenses
A6: One-off Cost (£) (once in forecast) | B6: 0 | C6: 0 | D6: 5000 | E6: Applied in first forecast month only

Sheet Scenario_Control
A1: Scenario Control
A3: Scenario Selector | B3: Base Case
A5: Forecast Months | B5: 12
A7: Notes
A8: Choose scenario in B3. Assumptions sheet drives growth rates and one-off cost.
A10: Revenue Growth % (MoM) | B10: =CHOOSE(MATCH(Scenario_Control!$B$3,Assumptions!$B$3:$D$3,0),Assumptions!B4,Assumptions!C4,Assumptions!D4) -> 0.05
A11: Expense Growth % (MoM) | B11: =CHOOSE(MATCH(Scenario_Control!$B$3,Assumptions!$B$3:$D$3,0),Assumptions!B5,Assumptions!C5,Assumptions!D5) -> 0.03
A12: One-off Cost (£) (once in forecast) | B12: =CHOOSE(MATCH(Scenario_Control!$B$3,Assumptions!$B$3:$D$3,0),Assumptions!B6,Assumptions!C6,Assumptions!D6) -> 0

Sheet Forecast_Model
A1: Forecast Model (build here)
A3: Month | B3: Revenue (£) | C3: Expenses (£) | D3: Net Profit (£) | E3: Cash Balance (£) | F3: Scenario Used
A4: {=DATEVALUE(LOOKUP(2,1/(Historical_Data!A:A<>""),Historical_Data!A:A)&"-01")} -> 45627 | B4: {=LOOKUP(2,1/(Historical_Data!B:B<>""),Historical_Data!B:B)} -> 50000 | C4: {=LOOKUP(2,1/(Historical_Data!C:C<>""),Historical_Data!C:C)} -> 34506 | D4: =B4-C4 -> 15494 | E4: {=LOOKUP(2,1/(Historical_Data!E:E<>""),Historical_Data!E:E)} -> 154703 | F4: =Scenario_Control!$B$3 -> Base Case
A5: =EDATE(A4,1) -> 45658 | B5: =B4*(1+Scenario_Control!B10) -> 52500 | C5: =C4*(Scenario_Control!B11+1)+Scenario_Control!B12 -> 35541.18 | D5: =B5-C5 -> 16958.82 | E5: =E4+D5 -> 171661.82 | F5: =Scenario_Control!$B$3 -> Base Case
A6: =EDATE(A5,1) -> 45689 | B6: =B5*(1+Scenario_Control!$B$10) -> 55125 | C6: =C5*(1+Scenario_Control!$B$11)+Scenario_Control!$B$12 -> 36607.415 | D6: =B6-C6 -> 18517.585 | E6: =E5+D6 -> 190179.4 | F6: =Scenario_Control!$B$3 -> Base Case
A7: =EDATE(A6,1) -> 45717 | B7: =B6*(1+Scenario_Control!$B$10) -> 57881.25 | C7: =C6*(1+Scenario_Control!$B$11)+Scenario_Control!$B$12 -> 37705.638 | D7: =B7-C7 -> 20175.612 | E7: =E6+D7 -> 210355.02 | F7: =Scenario_Control!$B$3 -> Base Case
A8: =EDATE(A7,1) -> 45748 | B8: =B7*(1+Scenario_Control!$B$10) -> 60775.312 | C8: =C7*(1+Scenario_Control!$B$11)+Scenario_Control!$B$12 -> 38836.807 | D8: =B8-C8 -> 21938.506 | E8: =E7+D8 -> 232293.52 | F8: =Scenario_Control!$B$3 -> Base Case
A9: =EDATE(A8,1) -> 45778 | B9: =B8*(1+Scenario_Control!$B$10) -> 63814.078 | C9: =C8*(1+Scenario_Control!$B$11)+Scenario_Control!$B$12 -> 40001.911 | D9: =B9-C9 -> 23812.167 | E9: =E8+D9 -> 256105.69 | F9: =Scenario_Control!$B$3 -> Base Case
A10: =EDATE(A9,1) -> 45809 | B10: =B9*(1+Scenario_Control!$B$10) -> 67004.782 | C10: =C9*(1+Scenario_Control!$B$11)+Scenario_Control!$B$12 -> 41201.969 | D10: =B10-C10 -> 25802.813 | E10: =E9+D10 -> 281908.5 | F10: =Scenario_Control!$B$3 -> Base Case
A11: =EDATE(A10,1) -> 45839 | B11: =B10*(1+Scenario_Control!$B$10) -> 70355.021 | C11: =C10*(1+Scenario_Control!$B$11)+Scenario_Control!$B$12 -> 42438.028 | D11: =B11-C11 -> 27916.994 | E11: =E10+D11 -> 309825.5 | F11: =Scenario_Control!$B$3 -> Base Case
A12: =EDATE(A11,1) -> 45870 | B12: =B11*(1+Scenario_Control!$B$10) -> 73872.772 | C12: =C11*(1+Scenario_Control!$B$11)+Scenario_Control!$B$12 -> 43711.168 | D12: =B12-C12 -> 30161.604 | E12: =E11+D12 -> 339987.1 | F12: =Scenario_Control!$B$3 -> Base Case
A13: =EDATE(A12,1) -> 45901 | B13: =B12*(1+Scenario_Control!$B$10) -> 77566.411 | C13: =C12*(1+Scenario_Control!$B$11)+Scenario_Control!$B$12 -> 45022.503 | D13: =B13-C13 -> 32543.907 | E13: =E12+D13 -> 372531.01 | F13: =Scenario_Control!$B$3 -> Base Case
A14: =EDATE(A13,1) -> 45931 | B14: =B13*(1+Scenario_Control!$B$10) -> 81444.731 | C14: =C13*(1+Scenario_Control!$B$11)+Scenario_Control!$B$12 -> 46373.179 | D14: =B14-C14 -> 35071.553 | E14: =E13+D14 -> 407602.56 | F14: =Scenario_Control!$B$3 -> Base Case
A15: =EDATE(A14,1) -> 45962 | B15: =B14*(1+Scenario_Control!$B$10) -> 85516.968 | C15: =C14*(1+Scenario_Control!$B$11)+Scenario_Control!$B$12 -> 47764.374 | D15: =B15-C15 -> 37752.594 | E15: =E14+D15 -> 445355.15 | F15: =Scenario_Control!$B$3 -> Base Case

Sheet Dashboard
A1: Dashboard (build charts & KPI cards here)
A3: Suggested KPIs
A4: Total Forecast Revenue | B4: =SUM(Forecast_Model!B4:B15) -> 795856.33
A5: Total Forecast Expenses | B5: =SUM(Forecast_Model!C4:C15) -> 489710.17
A6: End-of-Year Cash Balance | B6: =Forecast_Model!E15 -> 445355.15
A7: Lowest Cash Balance (Risk) | B7: =MIN(Forecast_Model!E4:E15) -> 154703
A8: Scenario Selected | B8: =Scenario_Control!B3 -> Base Case

Sheet Documentation
A1: Documentation
A3: 1) Purpose
A4: This Model forcast revenue, expenses, profit and cash balance for next 12 months
A6: 2) Inputs
A7: Historical Data of 12 months, Assumtions scenario of the best, woest cases, forecast model how the data change when apply the scenario.
A9: 3) Method
A10: We have three cases base, where we have normal growth, best, wehre we have high revenue and low expesnses, and last the woest, where we have low revenue and high expenses.
A12: 4) Scenarios
A13: Changing the scenario as exxplain in method, we changing the forcast model and see how after changing the scenario the model get affected.
